snowfake/__init__.py
snowfake/_version.py
snowfake/snowfake.py
snowfake-0.2.6.dist-info/AUTHORS.md
snowfake-0.2.6.dist-info/LICENSE
snowfake-0.2.6.dist-info/METADATA
snowfake-0.2.6.dist-info/WHEEL
snowfake-0.2.6.dist-info/top_level.txt
snowfake-0.2.6.dist-info/RECORD
